udplog
