Metadata-Version: 1.1
Name: udplog
Version: 0.1.1
Summary: UDPLog is a system for emitting application log events via UDP and shipping them via RabbitMQ or Scribe for further processing.
Home-page: https://github.com/mochi/udplog
Author: Ralph Meijer
Author-email: ralphm@ik.nu
License: MIT
Keywords: logging twisted udp scribe
Platform: UNKNOWN
Classifier: Development Status :: 4 - Beta
Classifier: Topic :: Utilities
Classifier: License :: OSI Approved :: MIT License
